{
  "employees": [
    {
      "id": 1,
      "name": "Jessica Younker",
      "position": "Supervisor",
      "locationId": 2
    },
    {
      "id": 2,
      "name": "Jordan Nelson",
      "position": "Owner",
      "locationId": 1
    },
    {
      "id": 3,
      "name": "Zoe LeBlanc",
      "position": "Crew",
      "locationId": 2
    },
    {
      "id": 4,
      "name": "Blaise Roberts",
      "position": "Crew",
      "locationId": 1
    }
  ],
  "locations": [
    {
      "id": 1,
      "name": "Nashville North",
      "address": "500 Circle Way"
    },
    {
      "id": 2,
      "name": "Nashville South",
      "address": "10101 Binary Court"
    }
  ],
  "animals": [
    {
      "id": 1,
      "name": "Foxy",
      "breed": "Golden Retriever",
      "ownerId": 2
    },
    {
      "id": 3,
      "name": "Snoopy",
      "breed": "Beagle",
      "ownerId": 3
    },
    {
      "name": "Barky",
      "breed": "Super Chow",
      "employeeId": 1,
      "id": 4
    },
    {
      "name": "Colby",
      "breed": "Lasso",
      "employeeId": 3,
      "id": 5
    }
  ],
  "owners": [
    {
      "id": 1,
      "name": "Ryan Tanay",
      "phone": "555-555-5551"
    },
    {
      "id": 2,
      "name": "Emma Beaton",
      "phone": "555-555-5552"
    },
    {
      "id": 3,
      "name": "Dani Adkins",
      "phone": "555-555-5553"
    },
    {
      "id": 4,
      "name": "Adam Oswalt",
      "phone": "555-555-5554"
    },
    {
      "id": 5,
      "name": "Fletcher Bangs",
      "phone": "555-555-5555"
    },
    {
      "id": 6,
      "name": "Angela Lee",
      "phone": "555-555-5556"
    }
  ]
}